dyes/.__init__.py.un~
dyes/__init__.py
dyes-0.0.1.dist-info/WHEEL
dyes-0.0.1.dist-info/METADATA
dyes-0.0.1.dist-info/RECORD
