Metadata-Version: 1.2
Name: dyes
Version: 0.0.1
Summary: A friendly alternative to pygments
Home-page: https://github.com/Carreau/dyes
License: UNKNOWN
Author: Matthias Bussonnier
Author-email: bussonniermatthias@gmail.com
